[
    {
        "_id": "${space_id}_22fY5x2GEeFBgwXnG",
        "name": "疫情情况通报",
        "body": "上海卫健委6月15日早通报：2022年6月14日0-24时，上海新增13例本土确诊病例和2例本土无症状感染者。其中1例确诊病例为既往无症状感染者转归，10例确诊病例和1例无症状感染者在隔离管控中发现，其余在风险人群筛查中发现，详情如下。\n\n　　**上海新增13例本土确诊**\n\n　　2022年6月14日0—24时，新增本土新冠肺炎确诊病例13例，含1例由既往无症状感染者转为确诊病例。新增治愈出院12例。\n\n　　**病例1**，居住于徐汇区，\n\n　　**病例2—病例10**，居住于宝山区，\n\n　　为本市闭环隔离管控人员，其间新冠病毒核酸检测结果异常，经疾控中心复核结果为阳性。经市级专家会诊，综合流行病学史、临床症状、实验室检测和影像学检查结果等，诊断为确诊病例。\n\n　　**病例11**，居住于杨浦区，\n\n　　**病例12**，居住于宝山区，\n\n　　在风险人群筛查中发现新冠病毒核酸检测结果异常，即被隔离管控。经疾控中心复核结果为阳性。经市级专家会诊，综合流行病学史、临床症状、实验室检测和影像学检查结果等，诊断为确诊病例。(6月14日已通报)\n\n　　**病例13**，居住于杨浦区，\n\n　　为此前报告的本土无症状感染者。经市级专家会诊，综合流行病学史、临床症状、实验室检测和影像学检查结果等，诊断为确诊病例。\n\n　　**上海新增2例本土无症状**\n\n　　2022年6月14日0—24时，新增本土无症状感染者2例。\n\n　　**无症状感染者1**，居住于徐汇区，为本市闭环隔离管控人员，其间新冠病毒核酸检测结果异常，经疾控中心复核结果为阳性，诊断为无症状感染者。\n\n　　**无症状感染者2**，居住于松江区，在风险人群筛查中发现新冠病毒核酸检测结果异常，即被隔离管控。经疾控中心复核结果为阳性，诊断为无症状感染者。(6月14日已通报)",
        "members": [
            "${space_owner_id}"
        ],
        "space": "6260d4ff102bc40032fa9b15",
        "created": {
            "$date": "2022-06-15T01:29:26.756Z"
        },
        "modified": {
            "$date": "2022-06-15T01:29:26.756Z"
        },
        "owner": "ChW7jsxfBvpMavdK2",
        "created_by": "ChW7jsxfBvpMavdK2",
        "modified_by": "ChW7jsxfBvpMavdK2",
        "company_id": "DP3zmEYJ7AyJH47GT",
        "company_ids": [
            "DP3zmEYJ7AyJH47GT"
        ]
    }
]